<?xml version="1.0" encoding="utf-8" ?>
<dwsync>
<file name="index.html" server="50.62.110.1" local="130440529426736648" remote="130440457200000000" Dst="2" />
<file name="Creating a Personal Marketing Plan.doc" server="50.62.110.1" local="130379900981080851" remote="130413868800000000" Dst="2" />
<file name="10 Steps to Defining Your Authentic Personal Brand.docx" server="50.62.110.1" local="130379901445544454" remote="130413868800000000" Dst="2" />
<file name="favicon.ico" server="50.62.110.1" local="130396528315310386" remote="130413869400000000" Dst="2" />
<file name="inventory.docx" server="50.62.110.1" local="130380032623829781" remote="130413870600000000" Dst="2" />
<file name="Personal Marketing plan.docx" server="50.62.110.1" local="130380047220169234" remote="130413870600000000" Dst="2" />
<file name="portfolio ideaschool.psd" server="50.62.110.1" local="130396499118892208" remote="130413871800000000" Dst="2" />
<file name="resume.pdf" server="50.62.110.1" local="130052471838037643" remote="130440340200000000" Dst="2" />
</dwsync>